langgraph_mcp/__init__.py
langgraph_mcp/assistant_graph.py
langgraph_mcp/assistant_graph_with_summarization.py
langgraph_mcp/build_router_graph.py
langgraph_mcp/configuration.py
langgraph_mcp/mcp_wrapper.py
langgraph_mcp/prompts.py
langgraph_mcp/retriever.py
langgraph_mcp/state.py
mseep_langgraph_mcp-0.0.2.dist-info/licenses/LICENSE
mseep_langgraph_mcp-0.0.2.dist-info/METADATA
mseep_langgraph_mcp-0.0.2.dist-info/WHEEL
mseep_langgraph_mcp-0.0.2.dist-info/top_level.txt
mseep_langgraph_mcp-0.0.2.dist-info/RECORD
