Metadata-Version: 2.4
Name: mseep-langgraph-mcp
Version: 0.0.2
Summary: LangGraph solution template for MCP
Author-email: mseep <support@skydeck.ai>
License: MIT
Requires-Python: >=3.12
License-File: LICENSE
Requires-Dist: asyncio>=3.4.3
Requires-Dist: langchain>=0.2.17
Requires-Dist: langchain-core>=0.3.21
Requires-Dist: langchain-milvus>=0.1.7
Requires-Dist: langchain-openai>=0.2.11
Requires-Dist: langgraph>=0.2.56
Requires-Dist: mcp>=1.0.0
Requires-Dist: openai>=1.57.0
Requires-Dist: python-dotenv>=1.0.1
Provides-Extra: dev
Requires-Dist: mypy>=1.11.1; extra == "dev"
Requires-Dist: ruff>=0.6.1; extra == "dev"
Requires-Dist: debugpy; extra == "dev"
Dynamic: license-file
